djing/__init__.py
djing/apps.py
djing/core/Actions/Action.py
djing/core/Actions/ActionCollection.py
djing/core/Actions/ActionResponse.py
djing/core/Actions/DestructiveAction.py
djing/core/Actions/DispatchAction.py
djing/core/Actions/__init__.py
djing/core/Authorizable.py
djing/core/AuthorizedToSee.py
djing/core/AuthorizesRequests.py
djing/core/Badge.py
djing/core/Card.py
djing/core/Cards/Help.py
djing/core/Cards/__init__.py
djing/core/Console/ActionCommand.py
djing/core/Console/BaseResourceCommand.py
djing/core/Console/CardCommand.py
djing/core/Console/DashboardCommand.py
djing/core/Console/DjingServiceProviderCommand.py
djing/core/Console/FieldCommand.py
djing/core/Console/FilterCommand.py
djing/core/Console/InstallCommand.py
djing/core/Console/LensCommand.py
djing/core/Console/PartitionMetricCommand.py
djing/core/Console/PolicyCommand.py
djing/core/Console/ProgressMetricCommand.py
djing/core/Console/PublishCommand.py
djing/core/Console/ResourceCommand.py
djing/core/Console/RuleCommand.py
djing/core/Console/TableMetricCommand.py
djing/core/Console/ValueMetricCommand.py
djing/core/Console/__init__.py
djing/core/Console/stubs/DjingServiceProvider.stub
djing/core/Console/stubs/action.stub
djing/core/Console/stubs/base-resource.stub
djing/core/Console/stubs/boolean-filter.stub
djing/core/Console/stubs/card/Card.stub
djing/core/Console/stubs/card/CardServiceProvider.stub
djing/core/Console/stubs/card/package.stub
djing/core/Console/stubs/card/src/css/card.stub
djing/core/Console/stubs/card/src/js/card.stub
djing/core/Console/stubs/card/src/js/components/Card.stub
djing/core/Console/stubs/card/vite.config.stub
djing/core/Console/stubs/config/app.stub
djing/core/Console/stubs/config/djing.stub
djing/core/Console/stubs/dashboard.stub
djing/core/Console/stubs/date-filter.stub
djing/core/Console/stubs/destructive-action.stub
djing/core/Console/stubs/field/Field.stub
djing/core/Console/stubs/field/FieldServiceProvider.stub
djing/core/Console/stubs/field/package.stub
djing-0.9.6.dist-info/LICENSE.md
djing-0.9.6.dist-info/METADATA
djing-0.9.6.dist-info/WHEEL
djing-0.9.6.dist-info/entry_points.txt
djing-0.9.6.dist-info/RECORD
