Metadata-Version: 2.3
Name: djing
Version: 0.9.6
Summary: djing admin panel
License: MIT
Author: Krunal Dodiya
Author-email: kunal.dodiya1@gmail.com
Requires-Python: >=3.10,<4.0
Classifier: License :: OSI Approved :: MIT License
Classifier: Programming Language :: Python :: 3
Classifier: Programming Language :: Python :: 3.10
Classifier: Programming Language :: Python :: 3.11
Classifier: Programming Language :: Python :: 3.12
Classifier: Programming Language :: Python :: 3.13
Requires-Dist: babel (>=2.16.0,<3.0.0)
Requires-Dist: cython (>=3.0.11,<4.0.0)
Requires-Dist: django (>=5.1.1,<6.0.0)
Requires-Dist: django-vite (>=3.0.4,<4.0.0)
Requires-Dist: inertia-django (>=0.6.0,<0.7.0)
Requires-Dist: pycryptodome (>=3.21.0,<4.0.0)
Requires-Dist: pyjinx (>=0.2.4,<0.3.0)
Requires-Dist: python-dotenv (>=1.0.1,<2.0.0)
Requires-Dist: whitenoise (>=6.7.0,<7.0.0)
Project-URL: documentation, https://djing.gitbook.io/docs
Project-URL: homepage, https://djing.vercel.app
Project-URL: repository, https://github.com/djing-admin/djing
